beaver_cli/__init__.py
beaver_cli/assets/error_screen.tcss
beaver_cli/assets/help.md
beaver_cli/assets/help_screen.tcss
beaver_cli/assets/settings_screen.tcss
beaver_cli/components/code.py
beaver_cli/components/error_message.py
beaver_cli/components/error_screen.py
beaver_cli/components/footer.py
beaver_cli/components/game_display.py
beaver_cli/components/header.py
beaver_cli/components/help_screen.py
beaver_cli/components/info_label.py
beaver_cli/components/link_to_code.py
beaver_cli/components/result_display.py
beaver_cli/components/settings_screen.py
beaver_cli/components/time_label.py
beaver_cli/main.py
beaver_cli/main.tcss
beaver_cli/schemas/__init__.py
beaver_cli/schemas/code_document.py
beaver_cli/schemas/common.py
beaver_cli/schemas/language.py
beaver_cli/schemas/statistic.py
beaver_cli/schemas/tags.py
beaver_cli/services/__init__.py
beaver_cli/services/api.py
beaver_cli/settings/__init__.py
beaver_cli/settings/settings.py
beaver_cli-0.1.6.dist-info/METADATA
beaver_cli-0.1.6.dist-info/WHEEL
beaver_cli-0.1.6.dist-info/entry_points.txt
beaver_cli-0.1.6.dist-info/RECORD
