Metadata-Version: 2.1
Name: beaver_cli
Version: 0.1.6
Summary: CLI application for Beaver project
Author: nikita zigman
Author-email: zigman.nikita@gmail.com
Requires-Python: >=3.12,<4.0
Classifier: Programming Language :: Python :: 3
Classifier: Programming Language :: Python :: 3.12
Classifier: Programming Language :: Python :: 3.13
Requires-Dist: pydantic (>=2.8.0,<3.0.0)
Requires-Dist: pydantic-settings (>=2.3.4,<3.0.0)
Requires-Dist: requests (>=2.32.3,<3.0.0)
Requires-Dist: syntax (>=0.1.3.2,<0.2.0.0)
Requires-Dist: textual-dev (>=1.5.1,<2.0.0)
Requires-Dist: textual[syntax] (>=0.70.0,<0.71.0)
Requires-Dist: typer (>=0.12.3,<0.13.0)
